[{"slug":"20240410-use-log4brains-to-manage-the-adrs","package":null,"title":"Use Log4brains to manage the ADRs","status":"accepted","creationDate":"2024-04-20T13:02:34.000Z","publicationDate":"2024-04-09T21:59:59.000Z"},{"slug":"blog/20240410-deploy-blog-using-astro","package":"blog","title":"Deploy blog using Astro","status":"accepted","creationDate":"2024-04-21T11:43:32.000Z","publicationDate":"2024-04-21T21:59:59.000Z"},{"slug":"20240603-use-plausible-for-website-analytics","package":null,"title":"Use Plausible for website analytics","status":"accepted","creationDate":"2024-06-03T19:23:21.000Z","publicationDate":"2024-06-03T21:59:59.000Z"}]